algo_crawler/__init__.py
algo_crawler/__main__.py
algo_crawler/exception.py
algo_crawler/model.py
algo_crawler/test.py
algo_crawler-0.0.2.dist-info/LICENSE
algo_crawler-0.0.2.dist-info/METADATA
algo_crawler-0.0.2.dist-info/WHEEL
algo_crawler-0.0.2.dist-info/top_level.txt
algo_crawler-0.0.2.dist-info/RECORD
